wmill/__init__.py
wmill/client.py
wmill/py.typed
wmill/s3_reader.py
wmill/s3_types.py
wmill-1.623.0.dist-info/METADATA
wmill-1.623.0.dist-info/WHEEL
wmill-1.623.0.dist-info/RECORD
