Metadata-Version: 2.1
Name: wmill
Version: 1.623.0
Summary: A client library for accessing Windmill server wrapping the Windmill client API
Home-page: https://windmill.dev
License: Apache-2.0
Author: Ruben Fiszel
Author-email: ruben@windmill.dev
Requires-Python: >=3.7,<4.0
Classifier: License :: OSI Approved :: Apache Software License
Classifier: Programming Language :: Python :: 3
Classifier: Programming Language :: Python :: 3.7
Classifier: Programming Language :: Python :: 3.8
Classifier: Programming Language :: Python :: 3.9
Classifier: Programming Language :: Python :: 3.10
Classifier: Programming Language :: Python :: 3.11
Requires-Dist: httpx (>=0.24)
Project-URL: Documentation, https://windmill.dev
